{
  "id": "2021-09-29_screen_english",
  "date": "2021-09-29",
  "corner": "screen_english",
  "corner_label": "Screen English",
  "title": "You still have your slot",
  "movie": "",
  "duration_sec": 822.84,
  "audio_url": "https://rtyzdyyfahddqshgyjvn.supabase.co/storage/v1/object/public/gmp-audio/2021-09-29_screen_english.mp3",
  "script": [
    {
      "start": 0.0,
      "end": 2.74,
      "text": "월간 굿모닝 팝 3개월 구독권 보내드릴게요."
    },
    {
      "start": 3.46,
      "end": 5.66,
      "text": "굿모닝 팝스에 사연 보내고 싶으신 분들"
    },
    {
      "start": 5.66,
      "end": 7.94,
      "text": "홈페이지 청취자 게시판에 남겨주세요."
    },
    {
      "start": 8.6,
      "end": 9.98,
      "text": "GMP로 영어실력 업!"
    },
    {
      "start": 10.26,
      "end": 11.12,
      "text": "에너지도 업!"
    },
    {
      "start": 11.66,
      "end": 13.64,
      "text": "고생 끝에 낙이 오듯이"
    },
    {
      "start": 13.64,
      "end": 15.46,
      "text": "이른 아침에 영어 공부 끝에"
    },
    {
      "start": 15.46,
      "end": 16.74,
      "text": "행운이 찾아옵니다."
    },
    {
      "start": 16.74,
      "end": 21.68,
      "text": "따뜻한 아메리카노 커플 세트 모바일 쿠폰 준비했어요."
    },
    {
      "start": 21.68,
      "end": 23.44,
      "text": "총 5분 뽑아서"
    },
    {
      "start": 23.44,
      "end": 26.68,
      "text": "한 분께 커피 쿠폰 2장씩 쏩니다."
    },
    {
      "start": 27.22,
      "end": 29.86,
      "text": "단문 50원과 장문 100원에 추가 요금이 부과되는"
    },
    {
      "start": 29.86,
      "end": 33.9,
      "text": "문자 샵 8910 아니면 샵 1061로 신청하시거나"
    },
    {
      "start": 33.9,
      "end": 36.64,
      "text": "무료인 콩 또는 마이케이로 참여해주세요."
    },
    {
      "start": 37.16,
      "end": 39.62,
      "text": "매주 일요일에 함께하는 코너인"
    },
    {
      "start": 39.62,
      "end": 42.26,
      "text": "GMP Short Essay 안내해드립니다."
    },
    {
      "start": 42.26,
      "end": 45.86,
      "text": "이번 주 10월 3일인 일요일까지는요."
    },
    {
      "start": 46.24,
      "end": 47.32,
      "text": "9월의 주제에"
    },
    {
      "start": 47.32,
      "end": 49.0,
      "text": "How to get over the stress"
    },
    {
      "start": 49.0,
      "end": 50.8,
      "text": "에 맞춰서 작성을 해주신"
    },
    {
      "start": 50.8,
      "end": 52.56,
      "text": "영화 에세이로 소개를 해드릴게요."
    },
    {
      "start": 53.24,
      "end": 55.52,
      "text": "그리고 이제 10월의 주제"
    },
    {
      "start": 55.52,
      "end": 57.04,
      "text": "미리 알려드려야 되겠죠."
    },
    {
      "start": 57.68,
      "end": 60.82,
      "text": "The most unique person around me"
    },
    {
      "start": 60.82,
      "end": 61.86,
      "text": "라는 주제입니다."
    },
    {
      "start": 62.52,
      "end": 65.34,
      "text": "여러분의 주변에 있는 가장 특이한 사람"
    },
    {
      "start": 65.34,
      "end": 67.62,
      "text": "소개해주시면 되는 시간이거든요."
    },
    {
      "start": 67.62,
      "end": 70.9,
      "text": "우리가 살아가면서 적어도 한두 명쯤은"
    },
    {
      "start": 70.9,
      "end": 72.7,
      "text": "정말 기억에 남을 만큼"
    },
    {
      "start": 72.7,
      "end": 74.84,
      "text": "독특한 사람을 만나게 되지 않습니까?"
    },
    {
      "start": 75.7,
      "end": 78.68,
      "text": "생각보다 가까운 사람일 수도 있겠고요."
    },
    {
      "start": 79.5,
      "end": 81.44,
      "text": "그 사람의 어떤 점이 인상적이고"
    },
    {
      "start": 81.44,
      "end": 83.28,
      "text": "그 이유가 무엇인지"
    },
    {
      "start": 83.28,
      "end": 85.36,
      "text": "한 세 줄 혹은 네 줄 정도로"
    },
    {
      "start": 85.36,
      "end": 86.84,
      "text": "에세이를 보내주시면 됩니다."
    },
    {
      "start": 87.5,
      "end": 89.9,
      "text": "저 왠지 매우 설레고 기대가 되거든요."
    },
    {
      "start": 90.14,
      "end": 91.06,
      "text": "기다리고 있을게요."
    },
    {
      "start": 91.58,
      "end": 92.56,
      "text": "굿모닝 팝스 홈페이지"
    },
    {
      "start": 92.56,
      "end": 94.04,
      "text": "청취자 게시판에 남겨주세요."
    },
    {
      "start": 94.04,
      "end": 104.33,
      "text": "스크린 잉글리쉬"
    },
    {
      "start": 104.33,
      "end": 124.14,
      "text": "비영화 구독 서비스"
    },
    {
      "start": 124.14,
      "end": 125.74,
      "text": "스크린 잉글리쉬 타임"
    },
    {
      "start": 125.74,
      "end": 127.74,
      "text": "9월에 함께하고 있는 영화는"
    },
    {
      "start": 127.74,
      "end": 130.74,
      "text": "2021 American Common of Age"
    },
    {
      "start": 130.74,
      "end": 132.0,
      "text": "코미디 드라마 film"
    },
    {
      "start": 132.0,
      "end": 134.32,
      "text": "that follows a hearing teenage girl"
    },
    {
      "start": 134.32,
      "end": 135.22,
      "text": "who is a CODA"
    },
    {
      "start": 135.22,
      "end": 137.0,
      "text": "and the name is CODA"
    },
    {
      "start": 137.0,
      "end": 138.36,
      "text": "안녕하세요"
    },
    {
      "start": 138.36,
      "end": 139.36,
      "text": "안녕하세요"
    },
    {
      "start": 139.36,
      "end": 140.72,
      "text": "굿모닝입니다"
    },
    {
      "start": 140.72,
      "end": 143.86,
      "text": "아니 1718님께서요"
    },
    {
      "start": 143.86,
      "end": 146.18,
      "text": "지난번에 로라쌤이"
    },
    {
      "start": 146.18,
      "end": 148.08,
      "text": "샤이퍼슨이라고 하던데"
    },
    {
      "start": 148.08,
      "end": 149.96,
      "text": "이것에 대해서 크리스쌤"
    },
    {
      "start": 149.96,
      "end": 151.2,
      "text": "어떻게 생각하시나요?"
    },
    {
      "start": 151.44,
      "end": 152.68,
      "text": "라고 질문을 해주셨어요."
    },
    {
      "start": 152.8,
      "end": 154.3,
      "text": "So she's asking me"
    },
    {
      "start": 154.3,
      "end": 155.42,
      "text": "what do I think of Laura"
    },
    {
      "start": 155.42,
      "end": 157.56,
      "text": "saying that she is a shy person."
    },
    {
      "start": 157.7,
      "end": 157.92,
      "text": "Yeah."
    },
    {
      "start": 158.64,
      "end": 159.94,
      "text": "제가 샤이퍼슨이라고"
    },
    {
      "start": 159.94,
      "end": 161.3,
      "text": "다른 코너에서"
    },
    {
      "start": 161.3,
      "end": 162.86,
      "text": "소개를 한 적이 있었거든요."
    },
    {
      "start": 163.8,
      "end": 164.9,
      "text": "How do you think?"
    },
    {
      "start": 165.16,
      "end": 166.1,
      "text": "What do I think about that?"
    },
    {
      "start": 166.28,
      "end": 167.8,
      "text": "Laura, yeah I think"
    },
    {
      "start": 167.8,
      "end": 169.66,
      "text": "she definitely has a shy side"
    },
    {
      "start": 169.66,
      "end": 171.22,
      "text": "and overall I would say"
    },
    {
      "start": 171.22,
      "end": 174.4,
      "text": "she's more shy than outgoing."
    },
    {
      "start": 174.4,
      "end": 175.8,
      "text": "I agree with that."
    },
    {
      "start": 175.8,
      "end": 176.2,
      "text": "아 그래요?"
    },
    {
      "start": 176.5,
      "end": 176.78,
      "text": "Yeah."
    },
    {
      "start": 177.46,
      "end": 178.22,
      "text": "저 사실은"
    },
    {
      "start": 178.22,
      "end": 179.38,
      "text": "half는 shy이고"
    },
    {
      "start": 179.38,
      "end": 181.54,
      "text": "half는 extroverted예요."
    },
    {
      "start": 181.66,
      "end": 181.92,
      "text": "Oh."
    },
    {
      "start": 182.12,
      "end": 183.46,
      "text": "It depends on the situation."
    },
    {
      "start": 183.68,
      "end": 185.16,
      "text": "I would say the same for me."
    },
    {
      "start": 185.24,
      "end": 185.42,
      "text": "Yeah."
    },
    {
      "start": 185.64,
      "end": 186.92,
      "text": "I'm shy, half shy,"
    },
    {
      "start": 187.08,
      "end": 187.94,
      "text": "half extroverted."
    },
    {
      "start": 188.02,
      "end": 188.3,
      "text": "Yeah."
    },
    {
      "start": 188.66,
      "end": 190.04,
      "text": "Depending on the situation."
    },
    {
      "start": 190.34,
      "end": 190.94,
      "text": "똑같네요."
    },
    {
      "start": 191.36,
      "end": 192.62,
      "text": "What is your blood type?"
    },
    {
      "start": 193.44,
      "end": 193.9,
      "text": "AB."
    },
    {
      "start": 194.3,
      "end": 195.1,
      "text": "AB, me too."
    },
    {
      "start": 195.34,
      "end": 195.94,
      "text": "진짜요?"
    },
    {
      "start": 195.98,
      "end": 197.12,
      "text": "AB, RH, minus."
    },
    {
      "start": 197.68,
      "end": 198.8,
      "text": "한국에 거의 없는 거."
    },
    {
      "start": 198.84,
      "end": 200.1,
      "text": "RH, plus예요 저는."
    },
    {
      "start": 200.22,
      "end": 200.88,
      "text": "아, plus."
    },
    {
      "start": 201.12,
      "end": 202.12,
      "text": "아, 그것만 다르네요."
    },
    {
      "start": 202.12,
      "end": 203.14,
      "text": "아, 그 미묘한"
    },
    {
      "start": 203.14,
      "end": 203.8,
      "text": "그 하나의 차이."
    },
    {
      "start": 203.8,
      "end": 204.9,
      "text": "아, 거의 똑같네요."
    },
    {
      "start": 204.9,
      "end": 205.28,
      "text": "네."
    },
    {
      "start": 205.7,
      "end": 207.46,
      "text": "아무튼 이런 우연이 있습니까?"
    },
    {
      "start": 208.04,
      "end": 209.98,
      "text": "그래서 이 성격도 반반인가 봐요."
    },
    {
      "start": 210.52,
      "end": 210.8,
      "text": "그쵸?"
    },
    {
      "start": 210.9,
      "end": 212.68,
      "text": "어느 날은 굉장히 뭔가 업되고"
    },
    {
      "start": 212.68,
      "end": 214.18,
      "text": "어느 날은 좀 차분하고"
    },
    {
      "start": 214.18,
      "end": 215.76,
      "text": "굉장히 쑥스럽다가도"
    },
    {
      "start": 215.76,
      "end": 217.48,
      "text": "갑자기 막 이렇게 오버해서"
    },
    {
      "start": 217.48,
      "end": 217.92,
      "text": "이야기하고"
    },
    {
      "start": 217.92,
      "end": 218.7,
      "text": "Isn't that difficult?"
    },
    {
      "start": 218.9,
      "end": 219.9,
      "text": "It's like a rollercoaster."
    },
    {
      "start": 220.02,
      "end": 220.28,
      "text": "Yeah."
    },
    {
      "start": 220.54,
      "end": 221.62,
      "text": "Up and down, up and down."
    },
    {
      "start": 221.68,
      "end": 222.78,
      "text": "멀 미나요, 정말."
    },
    {
      "start": 223.08,
      "end": 224.14,
      "text": "How do you control it?"
    },
    {
      "start": 224.54,
      "end": 226.12,
      "text": "I can't control it at all."
    },
    {
      "start": 226.14,
      "end": 227.08,
      "text": "치킨은 반반이지만"
    },
    {
      "start": 227.08,
      "end": 228.2,
      "text": "성격은 반반이면"
    },
    {
      "start": 228.2,
      "end": 229.48,
      "text": "갑자기 치킨 먹고 싶다."
    },
    {
      "start": 229.48,
      "end": 231.48,
      "text": "아무튼"
    },
    {
      "start": 231.48,
      "end": 233.42,
      "text": "We actually learned"
    },
    {
      "start": 233.42,
      "end": 234.52,
      "text": "about the actors."
    },
    {
      "start": 234.7,
      "end": 235.1,
      "text": "그쵸?"
    },
    {
      "start": 235.6,
      "end": 236.5,
      "text": "여태까지 우리가"
    },
    {
      "start": 236.5,
      "end": 237.2,
      "text": "이 영화의"
    },
    {
      "start": 237.2,
      "end": 238.38,
      "text": "액터들에 대해서"
    },
    {
      "start": 238.38,
      "end": 239.14,
      "text": "배웠었는데"
    },
    {
      "start": 239.14,
      "end": 240.58,
      "text": "특히 루비의"
    },
    {
      "start": 240.58,
      "end": 241.36,
      "text": "엄마 역할을"
    },
    {
      "start": 241.36,
      "end": 242.06,
      "text": "맡았던"
    },
    {
      "start": 242.06,
      "end": 243.42,
      "text": "Marlee Matlin"
    },
    {
      "start": 243.42,
      "end": 244.42,
      "text": "이라는 배우 있잖아요."
    },
    {
      "start": 244.78,
      "end": 244.96,
      "text": "Yeah."
    },
    {
      "start": 245.12,
      "end": 247.0,
      "text": "She's an Oscar winning actress."
    },
    {
      "start": 247.32,
      "end": 247.48,
      "text": "Yeah."
    },
    {
      "start": 247.48,
      "end": 248.52,
      "text": "The youngest ever"
    },
    {
      "start": 248.52,
      "end": 249.42,
      "text": "female actress"
    },
    {
      "start": 249.42,
      "end": 249.76,
      "text": "Yeah."
    },
    {
      "start": 249.76,
      "end": 251.04,
      "text": "To win an Oscar"
    },
    {
      "start": 251.04,
      "end": 252.24,
      "text": "for best actress."
    },
    {
      "start": 252.32,
      "end": 252.62,
      "text": "Right."
    },
    {
      "start": 252.62,
      "end": 253.58,
      "text": "She set a new record."
    },
    {
      "start": 253.58,
      "end": 255.12,
      "text": "그때가"
    },
    {
      "start": 255.12,
      "end": 256.76,
      "text": "34 years ago"
    },
    {
      "start": 256.76,
      "end": 258.02,
      "text": "이렇게 상을"
    },
    {
      "start": 258.02,
      "end": 258.98,
      "text": "받았다고 하더라고요."
    },
    {
      "start": 259.16,
      "end": 259.74,
      "text": "Long time ago."
    },
    {
      "start": 259.78,
      "end": 260.64,
      "text": "근데 원래는"
    },
    {
      "start": 260.64,
      "end": 261.32,
      "text": "이 영화에서"
    },
    {
      "start": 261.32,
      "end": 262.3,
      "text": "루비 아빠하고"
    },
    {
      "start": 262.3,
      "end": 264.02,
      "text": "루비 오빠 역할에"
    },
    {
      "start": 264.02,
      "end": 265.3,
      "text": "농인이 아닌"
    },
    {
      "start": 265.3,
      "end": 266.58,
      "text": "일반인 배우를"
    },
    {
      "start": 266.58,
      "end": 267.94,
      "text": "캐스팅하려고 했었대요."
    },
    {
      "start": 268.1,
      "end": 268.42,
      "text": "그런데"
    },
    {
      "start": 268.42,
      "end": 269.4,
      "text": "이 Marlee"
    },
    {
      "start": 269.4,
      "end": 270.18,
      "text": "Marlin"
    },
    {
      "start": 270.18,
      "end": 271.02,
      "text": "이라는 배우가"
    },
    {
      "start": 271.02,
      "end": 271.62,
      "text": "was totally"
    },
    {
      "start": 271.62,
      "end": 272.78,
      "text": "against that opinion."
    },
    {
      "start": 273.26,
      "end": 273.58,
      "text": "Yeah."
    },
    {
      "start": 273.58,
      "end": 274.96,
      "text": "She actually said"
    },
    {
      "start": 274.96,
      "end": 275.66,
      "text": "that if"
    },
    {
      "start": 275.66,
      "end": 276.66,
      "text": "you choose"
    },
    {
      "start": 276.66,
      "end": 277.86,
      "text": "a non-deaf actor"
    },
    {
      "start": 277.86,
      "end": 278.82,
      "text": "to play"
    },
    {
      "start": 278.82,
      "end": 279.54,
      "text": "루비's dad"
    },
    {
      "start": 279.54,
      "end": 280.8,
      "text": "I'm out."
    },
    {
      "start": 281.2,
      "end": 281.76,
      "text": "I will not"
    },
    {
      "start": 281.76,
      "end": 282.32,
      "text": "be in the movie"
    },
    {
      "start": 282.32,
      "end": 282.72,
      "text": "anymore."
    },
    {
      "start": 282.72,
      "end": 283.34,
      "text": "Wow."
    },
    {
      "start": 283.38,
      "end": 284.42,
      "text": "So she drew the line"
    },
    {
      "start": 284.42,
      "end": 285.76,
      "text": "and she said"
    },
    {
      "start": 285.76,
      "end": 286.2,
      "text": "that CODA"
    },
    {
      "start": 286.2,
      "end": 286.94,
      "text": "the special thing"
    },
    {
      "start": 286.94,
      "end": 287.66,
      "text": "about this movie"
    },
    {
      "start": 287.66,
      "end": 288.7,
      "text": "was that"
    },
    {
      "start": 288.7,
      "end": 289.54,
      "text": "it gave a rare"
    },
    {
      "start": 289.54,
      "end": 290.12,
      "text": "opportunity"
    },
    {
      "start": 290.12,
      "end": 291.24,
      "text": "to work with"
    },
    {
      "start": 291.24,
      "end": 292.2,
      "text": "a cast of"
    },
    {
      "start": 292.2,
      "end": 293.32,
      "text": "deaf actors"
    },
    {
      "start": 293.32,
      "end": 294.98,
      "text": "So other movies"
    },
    {
      "start": 294.98,
      "end": 295.98,
      "text": "they were always"
    },
    {
      "start": 295.98,
      "end": 296.82,
      "text": "in the background"
    },
    {
      "start": 296.82,
      "end": 297.88,
      "text": "or they just"
    },
    {
      "start": 297.88,
      "end": 298.56,
      "text": "played token"
    },
    {
      "start": 298.56,
      "end": 299.28,
      "text": "deaf characters"
    },
    {
      "start": 299.28,
      "end": 300.34,
      "text": "but this was"
    },
    {
      "start": 300.34,
      "end": 301.1,
      "text": "the first time"
    },
    {
      "start": 301.1,
      "end": 302.12,
      "text": "that deaf actors"
    },
    {
      "start": 302.12,
      "end": 303.04,
      "text": "actually carried"
    },
    {
      "start": 303.04,
      "end": 303.52,
      "text": "the film."
    },
    {
      "start": 303.9,
      "end": 304.3,
      "text": "They were the"
    },
    {
      "start": 304.3,
      "end": 305.82,
      "text": "main stars"
    },
    {
      "start": 305.82,
      "end": 306.8,
      "text": "of the movie."
    },
    {
      "start": 307.06,
      "end": 307.2,
      "text": "Oh."
    },
    {
      "start": 307.52,
      "end": 308.18,
      "text": "Main star"
    },
    {
      "start": 308.18,
      "end": 308.7,
      "text": "로서"
    },
    {
      "start": 308.7,
      "end": 309.74,
      "text": "영화에서"
    },
    {
      "start": 309.74,
      "end": 311.22,
      "text": "열연을 한 것에"
    },
    {
      "start": 311.22,
      "end": 311.52,
      "text": "대해서"
    },
    {
      "start": 311.52,
      "end": 312.7,
      "text": "아까 말씀하신"
    },
    {
      "start": 312.7,
      "end": 313.54,
      "text": "그 문장 중에"
    },
    {
      "start": 313.54,
      "end": 315.38,
      "text": "carried the film"
    },
    {
      "start": 315.38,
      "end": 316.06,
      "text": "이라는 표현이"
    },
    {
      "start": 316.06,
      "end": 316.68,
      "text": "들렸잖아요."
    },
    {
      "start": 316.9,
      "end": 317.94,
      "text": "They carried the film."
    },
    {
      "start": 318.18,
      "end": 318.94,
      "text": "The deaf actors"
    },
    {
      "start": 318.94,
      "end": 320.06,
      "text": "carried the film."
    },
    {
      "start": 320.18,
      "end": 320.56,
      "text": "아."
    },
    {
      "start": 320.98,
      "end": 321.52,
      "text": "그게 이제"
    },
    {
      "start": 321.52,
      "end": 322.3,
      "text": "메인 액터로서"
    },
    {
      "start": 322.3,
      "end": 323.26,
      "text": "영화를 찍었다"
    },
    {
      "start": 323.26,
      "end": 324.02,
      "text": "라고 해석하면"
    },
    {
      "start": 324.02,
      "end": 324.82,
      "text": "되는 문장인 거죠?"
    },
    {
      "start": 325.04,
      "end": 325.38,
      "text": "It means"
    },
    {
      "start": 325.38,
      "end": 325.88,
      "text": "they"
    },
    {
      "start": 325.88,
      "end": 327.12,
      "text": "이끌어갔어요."
    },
    {
      "start": 327.16,
      "end": 327.26,
      "text": "아."
    },
    {
      "start": 327.26,
      "end": 327.92,
      "text": "이끌어갔다."
    },
    {
      "start": 327.92,
      "end": 329.04,
      "text": "They led the film."
    },
    {
      "start": 329.16,
      "end": 330.2,
      "text": "They led the plot."
    },
    {
      "start": 330.4,
      "end": 330.42,
      "text": "그렇죠."
    },
    {
      "start": 330.58,
      "end": 331.44,
      "text": "주연으로서."
    },
    {
      "start": 331.54,
      "end": 332.18,
      "text": "주연으로서."
    },
    {
      "start": 332.18,
      "end": 332.88,
      "text": "Leading roles"
    },
    {
      "start": 332.88,
      "end": 333.44,
      "text": "를 한 거죠."
    },
    {
      "start": 333.58,
      "end": 334.16,
      "text": "주연들."
    },
    {
      "start": 334.38,
      "end": 334.7,
      "text": "Yeah."
    },
    {
      "start": 334.7,
      "end": 336.62,
      "text": "근데 이 내용을"
    },
    {
      "start": 336.62,
      "end": 337.64,
      "text": "들어보니까요."
    },
    {
      "start": 337.74,
      "end": 338.8,
      "text": "그 디렉터가"
    },
    {
      "start": 338.8,
      "end": 339.12,
      "text": "참"
    },
    {
      "start": 339.12,
      "end": 340.5,
      "text": "considerate 하다라는"
    },
    {
      "start": 340.5,
      "end": 341.4,
      "text": "생각이 듭니다."
    },
    {
      "start": 341.8,
      "end": 341.92,
      "text": "그렇죠?"
    },
    {
      "start": 342.18,
      "end": 342.4,
      "text": "Yeah."
    },
    {
      "start": 342.5,
      "end": 343.86,
      "text": "considers all the matters"
    },
    {
      "start": 343.86,
      "end": 345.44,
      "text": "all the elements"
    },
    {
      "start": 345.44,
      "end": 346.18,
      "text": "so deeply."
    },
    {
      "start": 346.54,
      "end": 347.68,
      "text": "He listened to her opinion"
    },
    {
      "start": 347.68,
      "end": 349.62,
      "text": "and he chose the deaf actor"
    },
    {
      "start": 349.62,
      "end": 351.08,
      "text": "to play Ruby's father."
    },
    {
      "start": 351.08,
      "end": 352.1,
      "text": "그래서 이렇게"
    },
    {
      "start": 352.1,
      "end": 353.28,
      "text": "아름다운 영화가"
    },
    {
      "start": 353.28,
      "end": 354.28,
      "text": "탄생이 된 거네요."
    },
    {
      "start": 354.86,
      "end": 354.98,
      "text": "네."
    },
    {
      "start": 355.1,
      "end": 355.94,
      "text": "먼저 오늘 장면"
    },
    {
      "start": 355.94,
      "end": 356.64,
      "text": "듣고 오겠습니다."
    },
    {
      "start": 356.64,
      "end": 357.96,
      "text": "These are"
    },
    {
      "start": 357.96,
      "end": 358.94,
      "text": "McKenna parents."
    },
    {
      "start": 360.54,
      "end": 361.4,
      "text": "Please tell them"
    },
    {
      "start": 361.4,
      "end": 362.3,
      "text": "your daughter is"
    },
    {
      "start": 362.3,
      "end": 363.38,
      "text": "very talented"
    },
    {
      "start": 363.38,
      "end": 364.56,
      "text": "and they're making"
    },
    {
      "start": 364.56,
      "end": 365.62,
      "text": "a terrible mistake"
    },
    {
      "start": 365.62,
      "end": 366.4,
      "text": "not sending her"
    },
    {
      "start": 366.4,
      "end": 367.12,
      "text": "off to school."
    },
    {
      "start": 367.7,
      "end": 368.82,
      "text": "I just sign the first part."
    },
    {
      "start": 369.58,
      "end": 369.98,
      "text": "I'm meeting"
    },
    {
      "start": 369.98,
      "end": 370.64,
      "text": "Miles at his"
    },
    {
      "start": 370.64,
      "end": 371.36,
      "text": "edition tomorrow."
    },
    {
      "start": 371.78,
      "end": 372.46,
      "text": "You still have your"
    },
    {
      "start": 372.46,
      "end": 372.82,
      "text": "slot."
    },
    {
      "start": 373.12,
      "end": 374.0,
      "text": "You have to stop."
    },
    {
      "start": 374.48,
      "end": 375.0,
      "text": "Okay."
    },
    {
      "start": 376.43,
      "end": 376.99,
      "text": "Thank you."
    },
    {
      "start": 378.58,
      "end": 378.78,
      "text": "네."
    },
    {
      "start": 379.12,
      "end": 380.6,
      "text": "어떤 듀엣 퍼포먼스가"
    },
    {
      "start": 380.6,
      "end": 381.54,
      "text": "끝나고 나서"
    },
    {
      "start": 381.54,
      "end": 383.04,
      "text": "가족들 앞에서"
    },
    {
      "start": 383.04,
      "end": 383.96,
      "text": "베르나르도"
    },
    {
      "start": 383.96,
      "end": 384.58,
      "text": "선생님이"
    },
    {
      "start": 384.58,
      "end": 385.14,
      "text": "이야기하는"
    },
    {
      "start": 385.14,
      "end": 386.1,
      "text": "내용이었는데"
    },
    {
      "start": 386.1,
      "end": 387.86,
      "text": "듀엣 퍼포먼스를"
    },
    {
      "start": 387.86,
      "end": 388.72,
      "text": "할 때 말이에요."
    },
    {
      "start": 389.08,
      "end": 389.74,
      "text": "If I were"
    },
    {
      "start": 389.74,
      "end": 391.0,
      "text": "her mom"
    },
    {
      "start": 391.0,
      "end": 391.84,
      "text": "or dad"
    },
    {
      "start": 391.84,
      "end": 392.98,
      "text": "I couldn't take"
    },
    {
      "start": 392.98,
      "end": 393.94,
      "text": "my eyes"
    },
    {
      "start": 393.94,
      "end": 394.26,
      "text": "off"
    },
    {
      "start": 394.26,
      "end": 395.34,
      "text": "Ruby."
    },
    {
      "start": 395.72,
      "end": 395.94,
      "text": "Yeah."
    },
    {
      "start": 396.4,
      "end": 397.0,
      "text": "Wouldn't you be"
    },
    {
      "start": 397.0,
      "end": 398.14,
      "text": "very very proud"
    },
    {
      "start": 398.14,
      "end": 399.24,
      "text": "of your daughter"
    },
    {
      "start": 399.24,
      "end": 400.6,
      "text": "up there on stage?"
    },
    {
      "start": 400.72,
      "end": 401.6,
      "text": "Even though"
    },
    {
      "start": 401.6,
      "end": 402.06,
      "text": "they couldn't"
    },
    {
      "start": 402.06,
      "end": 402.98,
      "text": "hear her voice"
    },
    {
      "start": 402.98,
      "end": 404.12,
      "text": "they saw her"
    },
    {
      "start": 404.12,
      "end": 404.84,
      "text": "perform in front"
    },
    {
      "start": 404.84,
      "end": 405.72,
      "text": "of a huge crowd"
    },
    {
      "start": 405.72,
      "end": 406.76,
      "text": "and they were"
    },
    {
      "start": 406.76,
      "end": 407.62,
      "text": "so proud of her."
    },
    {
      "start": 407.94,
      "end": 408.46,
      "text": "그런데"
    },
    {
      "start": 408.46,
      "end": 409.9,
      "text": "반전이 있었어요."
    },
    {
      "start": 410.08,
      "end": 411.04,
      "text": "이 부모님은"
    },
    {
      "start": 411.04,
      "end": 411.5,
      "text": "아무래도"
    },
    {
      "start": 411.5,
      "end": 411.96,
      "text": "이제"
    },
    {
      "start": 411.96,
      "end": 413.02,
      "text": "안 들리다 보니까"
    },
    {
      "start": 413.02,
      "end": 414.7,
      "text": "시간이 길어질수록"
    },
    {
      "start": 414.7,
      "end": 415.42,
      "text": "couldn't focus"
    },
    {
      "start": 415.42,
      "end": 416.2,
      "text": "on the performance."
    },
    {
      "start": 416.46,
      "end": 417.02,
      "text": "Yeah."
    },
    {
      "start": 417.4,
      "end": 418.24,
      "text": "You could tell"
    },
    {
      "start": 418.24,
      "end": 419.14,
      "text": "by their expressions."
    },
    {
      "start": 419.28,
      "end": 420.56,
      "text": "It was long."
    },
    {
      "start": 420.8,
      "end": 421.4,
      "text": "They couldn't"
    },
    {
      "start": 421.4,
      "end": 422.32,
      "text": "hear a word."
    },
    {
      "start": 422.54,
      "end": 423.66,
      "text": "So they"
    },
    {
      "start": 423.66,
      "end": 424.5,
      "text": "got distracted."
    },
    {
      "start": 424.66,
      "end": 424.92,
      "text": "그렇죠."
    },
    {
      "start": 425.22,
      "end": 426.02,
      "text": "그래서 수어로"
    },
    {
      "start": 426.02,
      "end": 426.78,
      "text": "오늘 저녁"
    },
    {
      "start": 426.78,
      "end": 427.4,
      "text": "뭐 먹을까"
    },
    {
      "start": 427.4,
      "end": 428.16,
      "text": "막 이런 대화를"
    },
    {
      "start": 428.16,
      "end": 428.68,
      "text": "하는 것도"
    },
    {
      "start": 428.68,
      "end": 429.48,
      "text": "기억이 나더라고요."
    },
    {
      "start": 429.6,
      "end": 429.74,
      "text": "Yeah."
    },
    {
      "start": 429.78,
      "end": 430.9,
      "text": "Just basic conversation."
    },
    {
      "start": 431.26,
      "end": 431.86,
      "text": "뭐 먹지?"
    },
    {
      "start": 432.34,
      "end": 433.2,
      "text": "What's for dinner?"
    },
    {
      "start": 433.38,
      "end": 433.58,
      "text": "여보."
    },
    {
      "start": 434.0,
      "end": 434.62,
      "text": "그런데"
    },
    {
      "start": 434.62,
      "end": 436.12,
      "text": "루비 오빠는"
    },
    {
      "start": 436.12,
      "end": 436.52,
      "text": "그래도"
    },
    {
      "start": 436.52,
      "end": 437.36,
      "text": "그중에 나름"
    },
    {
      "start": 437.36,
      "end": 437.68,
      "text": "되게"
    },
    {
      "start": 437.68,
      "end": 439.14,
      "text": "루비를 보면서"
    },
    {
      "start": 439.14,
      "end": 440.26,
      "text": "놀랬던 것 같아요."
    },
    {
      "start": 440.7,
      "end": 441.88,
      "text": "Was he impressed?"
    },
    {
      "start": 442.04,
      "end": 443.26,
      "text": "좀 알아챈 것 같더라고요."
    },
    {
      "start": 443.34,
      "end": 444.3,
      "text": "My sister."
    },
    {
      "start": 444.54,
      "end": 445.46,
      "text": "She has talent."
    },
    {
      "start": 446.5,
      "end": 447.58,
      "text": "So Miles and"
    },
    {
      "start": 447.58,
      "end": 448.42,
      "text": "루비가"
    },
    {
      "start": 448.42,
      "end": 449.52,
      "text": "finished the duet"
    },
    {
      "start": 449.52,
      "end": 450.06,
      "text": "performance"
    },
    {
      "start": 450.06,
      "end": 451.22,
      "text": "아주 very well"
    },
    {
      "start": 451.22,
      "end": 452.14,
      "text": "하게 끝냈습니다."
    },
    {
      "start": 452.18,
      "end": 453.44,
      "text": "They did a great job."
    },
    {
      "start": 453.5,
      "end": 455.2,
      "text": "They got a standing ovation."
    },
    {
      "start": 455.5,
      "end": 455.78,
      "text": "Yeah."
    },
    {
      "start": 455.98,
      "end": 456.46,
      "text": "Didn't they?"
    },
    {
      "start": 457.12,
      "end": 458.18,
      "text": "그랬던 것 같아요."
    },
    {
      "start": 458.38,
      "end": 458.58,
      "text": "Yeah."
    },
    {
      "start": 459.24,
      "end": 460.04,
      "text": "그래서 베르나르도"
    },
    {
      "start": 460.04,
      "end": 460.64,
      "text": "선생님이"
    },
    {
      "start": 460.64,
      "end": 461.7,
      "text": "complimented her"
    },
    {
      "start": 461.7,
      "end": 462.9,
      "text": "to her family."
    },
    {
      "start": 463.2,
      "end": 464.2,
      "text": "This is the first time"
    },
    {
      "start": 464.2,
      "end": 465.12,
      "text": "he saw her parents."
    },
    {
      "start": 465.12,
      "end": 465.34,
      "text": "Yeah."
    },
    {
      "start": 465.7,
      "end": 467.32,
      "text": "And he praised"
    },
    {
      "start": 467.32,
      "end": 467.86,
      "text": "their daughter."
    },
    {
      "start": 467.94,
      "end": 468.68,
      "text": "Your daughter"
    },
    {
      "start": 468.68,
      "end": 469.64,
      "text": "has an amazing talent."
    },
    {
      "start": 469.82,
      "end": 471.0,
      "text": "She should definitely"
    },
    {
      "start": 471.0,
      "end": 472.36,
      "text": "audition for music school."
    },
    {
      "start": 472.74,
      "end": 473.98,
      "text": "Send her to the audition."
    },
    {
      "start": 474.18,
      "end": 474.68,
      "text": "그렇죠."
    },
    {
      "start": 474.82,
      "end": 475.64,
      "text": "A little pressure."
    },
    {
      "start": 476.64,
      "end": 477.8,
      "text": "자, 일단"
    },
    {
      "start": 477.8,
      "end": 478.64,
      "text": "표현들 먼저"
    },
    {
      "start": 478.64,
      "end": 479.28,
      "text": "살펴볼게요."
    },
    {
      "start": 480.06,
      "end": 481.38,
      "text": "My kind of parents."
    },
    {
      "start": 481.76,
      "end": 483.1,
      "text": "My kind of parents."
    },
    {
      "start": 483.12,
      "end": 484.22,
      "text": "My kind of parents."
    },
    {
      "start": 484.92,
      "end": 485.76,
      "text": "내 스타일이다."
    },
    {
      "start": 486.06,
      "end": 487.34,
      "text": "내 스타일의 부모님이다."
    },
    {
      "start": 487.62,
      "end": 488.56,
      "text": "라는 말이 되겠습니다."
    },
    {
      "start": 488.86,
      "end": 490.16,
      "text": "That's my kind of"
    },
    {
      "start": 490.16,
      "end": 490.96,
      "text": "radio host."
    },
    {
      "start": 491.12,
      "end": 492.38,
      "text": "내 스타일의"
    },
    {
      "start": 492.38,
      "end": 493.3,
      "text": "radio host다."
    },
    {
      "start": 494.06,
      "end": 494.8,
      "text": "청취자들"
    },
    {
      "start": 494.8,
      "end": 496.22,
      "text": "이렇게 문자 보내면"
    },
    {
      "start": 496.22,
      "end": 497.3,
      "text": "기분 좋지 않을까요?"
    },
    {
      "start": 497.36,
      "end": 498.26,
      "text": "너무 좋을 것 같아요."
    },
    {
      "start": 498.52,
      "end": 499.2,
      "text": "부탁드립니다."
    },
    {
      "start": 499.66,
      "end": 499.94,
      "text": "좋아요."
    },
    {
      "start": 500.52,
      "end": 500.9,
      "text": "Please."
    },
    {
      "start": 501.08,
      "end": 501.28,
      "text": "네."
    },
    {
      "start": 502.0,
      "end": 503.62,
      "text": "Making a terrible mistake."
    },
    {
      "start": 503.86,
      "end": 505.76,
      "text": "Making a terrible mistake."
    },
    {
      "start": 506.12,
      "end": 507.44,
      "text": "끔찍한 실수를"
    },
    {
      "start": 507.44,
      "end": 508.82,
      "text": "저지르는 것."
    },
    {
      "start": 508.82,
      "end": 510.33,
      "text": "still have"
    },
    {
      "start": 510.33,
      "end": 511.03,
      "text": "your slot."
    },
    {
      "start": 511.35,
      "end": 512.47,
      "text": "Slot라는 단어가"
    },
    {
      "start": 512.47,
      "end": 513.03,
      "text": "들렸잖아요."
    },
    {
      "start": 513.27,
      "end": 513.57,
      "text": "Slot."
    },
    {
      "start": 513.79,
      "end": 514.93,
      "text": "S-L-O-T"
    },
    {
      "start": 514.93,
      "end": 515.61,
      "text": "라고 해서"
    },
    {
      "start": 515.61,
      "end": 516.45,
      "text": "자리,"
    },
    {
      "start": 516.91,
      "end": 517.27,
      "text": "시간,"
    },
    {
      "start": 517.41,
      "end": 518.03,
      "text": "혹은 틈"
    },
    {
      "start": 518.03,
      "end": 519.07,
      "text": "이라는 의미니까"
    },
    {
      "start": 519.07,
      "end": 520.31,
      "text": "still have"
    },
    {
      "start": 520.31,
      "end": 521.13,
      "text": "your slot."
    },
    {
      "start": 521.49,
      "end": 521.79,
      "text": "아직"
    },
    {
      "start": 521.79,
      "end": 522.83,
      "text": "네 자리 있어."
    },
    {
      "start": 523.07,
      "end": 523.67,
      "text": "라는 의미로"
    },
    {
      "start": 523.67,
      "end": 524.79,
      "text": "해석하시면 되겠네요."
    },
    {
      "start": 524.87,
      "end": 525.67,
      "text": "At the audition."
    },
    {
      "start": 525.85,
      "end": 527.17,
      "text": "바로 그거죠."
    },
    {
      "start": 527.59,
      "end": 527.71,
      "text": "네."
    },
    {
      "start": 527.95,
      "end": 528.37,
      "text": "이 장면"
    },
    {
      "start": 528.37,
      "end": 529.23,
      "text": "다시 한번 들어볼게요."
    },
    {
      "start": 529.23,
      "end": 553.55,
      "text": "베르나르도 선생님이"
    },
    {
      "start": 553.55,
      "end": 554.17,
      "text": "아주"
    },
    {
      "start": 554.17,
      "end": 556.09,
      "text": "satisfied with the performance"
    },
    {
      "start": 556.09,
      "end": 556.69,
      "text": "했나봐요."
    },
    {
      "start": 556.79,
      "end": 557.41,
      "text": "Very"
    },
    {
      "start": 557.41,
      "end": 558.13,
      "text": "흐뭇해."
    },
    {
      "start": 558.27,
      "end": 559.59,
      "text": "아주 진정성 있게"
    },
    {
      "start": 559.59,
      "end": 560.79,
      "text": "칭찬을 하고 계시더라고요."
    },
    {
      "start": 561.49,
      "end": 563.37,
      "text": "These are my kind of parents."
    },
    {
      "start": 563.63,
      "end": 565.79,
      "text": "첫 번째 문장이었습니다."
    },
    {
      "start": 566.01,
      "end": 568.25,
      "text": "These are my kind of parents."
    },
    {
      "start": 568.87,
      "end": 569.63,
      "text": "너희 부모님"
    },
    {
      "start": 569.63,
      "end": 571.01,
      "text": "딱 내 스타일이다."
    },
    {
      "start": 572.2,
      "end": 573.46,
      "text": "Please tell them."
    },
    {
      "start": 573.66,
      "end": 574.46,
      "text": "Please tell them."
    },
    {
      "start": 574.7,
      "end": 576.24,
      "text": "Your daughter is very talented"
    },
    {
      "start": 576.24,
      "end": 577.8,
      "text": "and you're making"
    },
    {
      "start": 577.8,
      "end": 578.66,
      "text": "a terrible mistake"
    },
    {
      "start": 578.66,
      "end": 580.06,
      "text": "not sending her off to school."
    },
    {
      "start": 580.4,
      "end": 581.4,
      "text": "와 이제"
    },
    {
      "start": 581.4,
      "end": 582.4,
      "text": "루비한테"
    },
    {
      "start": 582.4,
      "end": 583.84,
      "text": "통역을 부탁하는 거예요."
    },
    {
      "start": 584.28,
      "end": 585.18,
      "text": "Please tell them."
    },
    {
      "start": 586.04,
      "end": 586.58,
      "text": "부모님께"
    },
    {
      "start": 586.58,
      "end": 587.7,
      "text": "이렇게 전해드리렴."
    },
    {
      "start": 588.04,
      "end": 588.68,
      "text": "Your daughter"
    },
    {
      "start": 588.68,
      "end": 590.28,
      "text": "is very talented."
    },
    {
      "start": 591.0,
      "end": 591.46,
      "text": "따님은"
    },
    {
      "start": 591.46,
      "end": 592.78,
      "text": "매우 재능이 있고"
    },
    {
      "start": 592.78,
      "end": 594.2,
      "text": "and you're making"
    },
    {
      "start": 594.2,
      "end": 595.58,
      "text": "a terrible mistake."
    },
    {
      "start": 596.14,
      "end": 596.8,
      "text": "당신들은"
    },
    {
      "start": 596.8,
      "end": 598.2,
      "text": "끔찍한 실수를"
    },
    {
      "start": 598.2,
      "end": 599.6,
      "text": "저지르는 거라고요."
    },
    {
      "start": 599.6,
      "end": 601.06,
      "text": "Not sending her"
    },
    {
      "start": 601.06,
      "end": 602.14,
      "text": "off to school."
    },
    {
      "start": 603.0,
      "end": 604.52,
      "text": "대학을 안 보내는 것은"
    },
    {
      "start": 604.52,
      "end": 606.22,
      "text": "끔찍한 실수를"
    },
    {
      "start": 606.22,
      "end": 607.56,
      "text": "저지르는 거라고"
    },
    {
      "start": 607.56,
      "end": 608.88,
      "text": "전해드리렴."
    },
    {
      "start": 609.12,
      "end": 609.88,
      "text": "I like Bernardo."
    },
    {
      "start": 610.1,
      "end": 611.42,
      "text": "He's very straightforward."
    },
    {
      "start": 611.9,
      "end": 613.12,
      "text": "This is his first time"
    },
    {
      "start": 613.12,
      "end": 613.48,
      "text": "meeting them."
    },
    {
      "start": 613.62,
      "end": 615.12,
      "text": "But he's being very honest."
    },
    {
      "start": 615.18,
      "end": 615.68,
      "text": "그러네요."
    },
    {
      "start": 615.88,
      "end": 616.56,
      "text": "첫 만남에"
    },
    {
      "start": 616.56,
      "end": 617.6,
      "text": "아주 정직하게"
    },
    {
      "start": 617.6,
      "end": 618.36,
      "text": "솔직하게"
    },
    {
      "start": 618.36,
      "end": 619.14,
      "text": "이야기를 하십니다."
    },
    {
      "start": 619.3,
      "end": 620.26,
      "text": "Brutally honest."
    },
    {
      "start": 621.61,
      "end": 623.23,
      "text": "I'll just sign the first part."
    },
    {
      "start": 624.21,
      "end": 624.77,
      "text": "아무래도"
    },
    {
      "start": 624.77,
      "end": 626.19,
      "text": "sign language에서의"
    },
    {
      "start": 626.19,
      "end": 627.37,
      "text": "그 sign의 의미를"
    },
    {
      "start": 627.37,
      "end": 628.31,
      "text": "동사적으로"
    },
    {
      "start": 628.31,
      "end": 629.01,
      "text": "활용을 한 겁니다."
    },
    {
      "start": 629.01,
      "end": 629.65,
      "text": "Sign."
    },
    {
      "start": 629.97,
      "end": 631.75,
      "text": "I'll just sign the first part."
    },
    {
      "start": 631.95,
      "end": 632.35,
      "text": "만약에"
    },
    {
      "start": 632.35,
      "end": 633.71,
      "text": "일반적으로 우리가 쓴다면"
    },
    {
      "start": 633.71,
      "end": 635.71,
      "text": "I'll just tell the first part"
    },
    {
      "start": 635.71,
      "end": 636.55,
      "text": "라고 하면 되겠죠."
    },
    {
      "start": 636.65,
      "end": 636.83,
      "text": "Yeah."
    },
    {
      "start": 636.89,
      "end": 637.87,
      "text": "I'll just interpret"
    },
    {
      "start": 637.87,
      "end": 639.75,
      "text": "or translate the first part."
    },
    {
      "start": 639.89,
      "end": 640.19,
      "text": "맞아요."
    },
    {
      "start": 640.35,
      "end": 641.95,
      "text": "I'll leave the second part out"
    },
    {
      "start": 641.95,
      "end": 643.49,
      "text": "because that will make them"
    },
    {
      "start": 643.49,
      "end": 644.63,
      "text": "feel very bad"
    },
    {
      "start": 644.63,
      "end": 645.79,
      "text": "and very sorry."
    },
    {
      "start": 645.91,
      "end": 646.13,
      "text": "그렇죠."
    },
    {
      "start": 646.33,
      "end": 647.99,
      "text": "학교 진학 문제는 빼고"
    },
    {
      "start": 647.99,
      "end": 649.75,
      "text": "Your daughter is very talented"
    },
    {
      "start": 649.75,
      "end": 651.09,
      "text": "라고 하신 말씀만"
    },
    {
      "start": 651.09,
      "end": 651.73,
      "text": "전할게요."
    },
    {
      "start": 651.87,
      "end": 653.07,
      "text": "라는 의도가 되겠습니다."
    },
    {
      "start": 653.29,
      "end": 654.15,
      "text": "그렇게 많이 하잖아요."
    },
    {
      "start": 654.37,
      "end": 655.53,
      "text": "뭐 동역하거나"
    },
    {
      "start": 655.53,
      "end": 657.09,
      "text": "기분 좋은 부분만."
    },
    {
      "start": 657.09,
      "end": 658.83,
      "text": "White lie가 되겠네요."
    },
    {
      "start": 658.95,
      "end": 659.69,
      "text": "White lie."
    },
    {
      "start": 659.69,
      "end": 663.17,
      "text": "I'm meeting Miles"
    },
    {
      "start": 663.17,
      "end": 664.65,
      "text": "at his audition tomorrow."
    },
    {
      "start": 664.89,
      "end": 665.01,
      "text": "네."
    },
    {
      "start": 665.09,
      "end": 666.55,
      "text": "베르나르도 선생님이"
    },
    {
      "start": 666.55,
      "end": 667.39,
      "text": "하는 말이"
    },
    {
      "start": 667.39,
      "end": 668.85,
      "text": "I'm meeting Miles"
    },
    {
      "start": 668.85,
      "end": 670.33,
      "text": "at his audition tomorrow."
    },
    {
      "start": 670.41,
      "end": 670.87,
      "text": "Miles."
    },
    {
      "start": 671.29,
      "end": 672.09,
      "text": "Miles가"
    },
    {
      "start": 672.09,
      "end": 673.35,
      "text": "He's going to audition"
    },
    {
      "start": 673.35,
      "end": 674.53,
      "text": "for the same school."
    },
    {
      "start": 674.67,
      "end": 674.89,
      "text": "네."
    },
    {
      "start": 675.17,
      "end": 675.61,
      "text": "내일"
    },
    {
      "start": 675.61,
      "end": 676.97,
      "text": "그 오디션을"
    },
    {
      "start": 676.97,
      "end": 678.09,
      "text": "보는가 봅니다."
    },
    {
      "start": 678.37,
      "end": 678.59,
      "text": "그래서"
    },
    {
      "start": 678.59,
      "end": 679.53,
      "text": "I'm meeting Miles"
    },
    {
      "start": 679.53,
      "end": 680.71,
      "text": "at his audition tomorrow"
    },
    {
      "start": 680.71,
      "end": 681.43,
      "text": "라고 하신 거예요."
    },
    {
      "start": 681.87,
      "end": 683.03,
      "text": "내일 오디션에서"
    },
    {
      "start": 683.03,
      "end": 684.25,
      "text": "Miles를 만날 거야."
    },
    {
      "start": 685.17,
      "end": 686.27,
      "text": "You still have your slot."
    },
    {
      "start": 686.49,
      "end": 688.49,
      "text": "You still have your slot."
    },
    {
      "start": 688.65,
      "end": 689.23,
      "text": "라고 했으니까"
    },
    {
      "start": 689.23,
      "end": 691.15,
      "text": "네 자리 여전히 있어."
    },
    {
      "start": 691.71,
      "end": 692.95,
      "text": "Well, that's more incentive"
    },
    {
      "start": 692.95,
      "end": 694.53,
      "text": "to take that slot."
    },
    {
      "start": 694.69,
      "end": 694.81,
      "text": "Yeah."
    },
    {
      "start": 695.05,
      "end": 696.07,
      "text": "Miles is also"
    },
    {
      "start": 696.07,
      "end": 696.73,
      "text": "auditioning for"
    },
    {
      "start": 696.73,
      "end": 697.95,
      "text": "Berklee School of Music."
    },
    {
      "start": 698.23,
      "end": 699.25,
      "text": "If you both"
    },
    {
      "start": 699.25,
      "end": 699.79,
      "text": "합격,"
    },
    {
      "start": 699.99,
      "end": 700.99,
      "text": "if you both pass,"
    },
    {
      "start": 701.25,
      "end": 701.75,
      "text": "you can go to"
    },
    {
      "start": 701.75,
      "end": 702.65,
      "text": "the same college"
    },
    {
      "start": 702.65,
      "end": 703.57,
      "text": "together."
    },
    {
      "start": 704.49,
      "end": 705.11,
      "text": "화해했죠."
    },
    {
      "start": 705.33,
      "end": 705.57,
      "text": "네."
    },
    {
      "start": 705.75,
      "end": 706.39,
      "text": "화해했어요."
    },
    {
      "start": 706.57,
      "end": 706.73,
      "text": "Yeah."
    },
    {
      "start": 706.79,
      "end": 707.25,
      "text": "They fought,"
    },
    {
      "start": 707.35,
      "end": 708.33,
      "text": "but now they're friends again."
    },
    {
      "start": 708.33,
      "end": 709.87,
      "text": "They like each other again."
    },
    {
      "start": 709.87,
      "end": 710.67,
      "text": "그러니까요."
    },
    {
      "start": 711.62,
      "end": 712.74,
      "text": "You have to stop."
    },
    {
      "start": 713.2,
      "end": 713.78,
      "text": "루비가"
    },
    {
      "start": 713.78,
      "end": 715.68,
      "text": "선생님의 말씀을 끊습니다."
    },
    {
      "start": 715.82,
      "end": 716.6,
      "text": "You have to stop."
    },
    {
      "start": 716.9,
      "end": 717.54,
      "text": "그만하세요."
    },
    {
      "start": 718.54,
      "end": 718.96,
      "text": "Okay."
    },
    {
      "start": 719.52,
      "end": 720.04,
      "text": "알았어."
    },
    {
      "start": 721.24,
      "end": 721.56,
      "text": "Okay."
    },
    {
      "start": 721.98,
      "end": 722.46,
      "text": "Fine."
    },
    {
      "start": 724.01,
      "end": 724.73,
      "text": "But thank you."
    },
    {
      "start": 724.95,
      "end": 725.19,
      "text": "아,"
    },
    {
      "start": 725.37,
      "end": 726.25,
      "text": "이 마무리 좋았어요."
    },
    {
      "start": 726.43,
      "end": 726.59,
      "text": "그죠?"
    },
    {
      "start": 727.05,
      "end": 727.91,
      "text": "But thank you."
    },
    {
      "start": 728.09,
      "end": 729.37,
      "text": "그래도 감사해요."
    },
    {
      "start": 729.55,
      "end": 730.79,
      "text": "말씀은 감사해요."
    },
    {
      "start": 730.93,
      "end": 731.75,
      "text": "라는 말이 되겠죠."
    },
    {
      "start": 731.93,
      "end": 732.01,
      "text": "Yeah."
    },
    {
      "start": 732.07,
      "end": 732.89,
      "text": "She appreciates"
    },
    {
      "start": 732.89,
      "end": 733.81,
      "text": "his efforts."
    },
    {
      "start": 734.35,
      "end": 734.75,
      "text": "네."
    },
    {
      "start": 734.75,
      "end": 735.43,
      "text": "아직까지도"
    },
    {
      "start": 735.43,
      "end": 736.15,
      "text": "이렇게 보니까"
    },
    {
      "start": 736.15,
      "end": 737.05,
      "text": "루비는"
    },
    {
      "start": 737.05,
      "end": 738.15,
      "text": "seemed to have"
    },
    {
      "start": 738.15,
      "end": 738.65,
      "text": "given up"
    },
    {
      "start": 738.65,
      "end": 739.91,
      "text": "on going to college."
    },
    {
      "start": 740.07,
      "end": 740.81,
      "text": "She did give up."
    },
    {
      "start": 740.87,
      "end": 741.69,
      "text": "Just because"
    },
    {
      "start": 741.69,
      "end": 742.41,
      "text": "she feels"
    },
    {
      "start": 742.41,
      "end": 743.47,
      "text": "obligated"
    },
    {
      "start": 743.47,
      "end": 744.31,
      "text": "to help her parents."
    },
    {
      "start": 744.41,
      "end": 744.85,
      "text": "Parents."
    },
    {
      "start": 745.01,
      "end": 745.13,
      "text": "Yeah."
    },
    {
      "start": 745.15,
      "end": 745.53,
      "text": "Family."
    },
    {
      "start": 745.73,
      "end": 746.13,
      "text": "She doesn't know"
    },
    {
      "start": 746.13,
      "end": 746.81,
      "text": "what they would do"
    },
    {
      "start": 746.81,
      "end": 747.51,
      "text": "without her"
    },
    {
      "start": 747.51,
      "end": 748.37,
      "text": "because they have"
    },
    {
      "start": 748.37,
      "end": 749.97,
      "text": "lived for so long"
    },
    {
      "start": 749.97,
      "end": 750.57,
      "text": "with her help."
    },
    {
      "start": 750.73,
      "end": 751.91,
      "text": "To consider it"
    },
    {
      "start": 751.91,
      "end": 752.59,
      "text": "하기도 하네요."
    },
    {
      "start": 752.73,
      "end": 752.83,
      "text": "그렇죠?"
    },
    {
      "start": 752.95,
      "end": 753.07,
      "text": "Yeah."
    },
    {
      "start": 753.17,
      "end": 753.47,
      "text": "Come on."
    },
    {
      "start": 753.49,
      "end": 753.93,
      "text": "You have to follow"
    },
    {
      "start": 753.93,
      "end": 754.61,
      "text": "your own dreams."
    },
    {
      "start": 754.93,
      "end": 756.23,
      "text": "꿈을 쫓아가야 할 텐데."
    },
    {
      "start": 756.49,
      "end": 756.71,
      "text": "그렇죠?"
    },
    {
      "start": 756.87,
      "end": 757.87,
      "text": "응원하는 마음으로."
    },
    {
      "start": 757.87,
      "end": 758.79,
      "text": "Come on."
    },
    {
      "start": 759.39,
      "end": 759.53,
      "text": "네."
    },
    {
      "start": 759.61,
      "end": 760.01,
      "text": "이 장면"
    },
    {
      "start": 760.01,
      "end": 760.89,
      "text": "한 번 더 들어볼게요."
    },
    {
      "start": 760.89,
      "end": 760.99,
      "text": "Come on."
    },
    {
      "start": 760.99,
      "end": 761.63,
      "text": "Come on."
    },
    {
      "start": 761.63,
      "end": 763.07,
      "text": "These are my kind of parents."
    },
    {
      "start": 764.71,
      "end": 765.49,
      "text": "Please tell them"
    },
    {
      "start": 765.49,
      "end": 767.51,
      "text": "your daughter is very talented."
    },
    {
      "start": 768.19,
      "end": 769.77,
      "text": "And they're making a terrible mistake"
    },
    {
      "start": 769.77,
      "end": 771.25,
      "text": "not sending her off to school."
    },
    {
      "start": 771.83,
      "end": 772.95,
      "text": "I'll just sign the first part."
    },
    {
      "start": 773.71,
      "end": 775.51,
      "text": "I'm meeting miles at his edition tomorrow."
    },
    {
      "start": 775.91,
      "end": 776.97,
      "text": "You still have your slot."
    },
    {
      "start": 777.25,
      "end": 778.13,
      "text": "You have to stop."
    },
    {
      "start": 778.62,
      "end": 779.14,
      "text": "Okay."
    },
    {
      "start": 780.14,
      "end": 781.13,
      "text": "Thank you."
    },
    {
      "start": 781.13,
      "end": 784.58,
      "text": "8647님께서"
    },
    {
      "start": 784.58,
      "end": 785.94,
      "text": "백신 맞고"
    },
    {
      "start": 785.94,
      "end": 787.02,
      "text": "오늘은 쉴까"
    },
    {
      "start": 787.02,
      "end": 788.56,
      "text": "하는 유혹을 물리치고"
    },
    {
      "start": 788.56,
      "end": 789.66,
      "text": "입을 박차고"
    },
    {
      "start": 789.66,
      "end": 790.38,
      "text": "일어났어요."
    },
    {
      "start": 790.8,
      "end": 791.28,
      "text": "하루라도"
    },
    {
      "start": 791.28,
      "end": 791.88,
      "text": "밀리면"
    },
    {
      "start": 791.88,
      "end": 792.72,
      "text": "쉬르니까요."
    },
    {
      "start": 793.1,
      "end": 793.82,
      "text": "본방사수의"
    },
    {
      "start": 793.82,
      "end": 794.5,
      "text": "매력 또한"
    },
    {
      "start": 794.5,
      "end": 795.04,
      "text": "큽니다."
    },
    {
      "start": 795.46,
      "end": 795.92,
      "text": "조쌤"
    },
    {
      "start": 795.92,
      "end": 796.42,
      "text": "크쌤"
    },
    {
      "start": 796.42,
      "end": 796.82,
      "text": "최고"
    },
    {
      "start": 796.82,
      "end": 798.0,
      "text": "웃음 웃음"
    },
    {
      "start": 798.0,
      "end": 799.5,
      "text": "Thank you so much."
    },
    {
      "start": 799.74,
      "end": 799.92,
      "text": "네."
    },
    {
      "start": 800.28,
      "end": 800.8,
      "text": "그거 아세요?"
    },
    {
      "start": 800.96,
      "end": 801.6,
      "text": "매번"
    },
    {
      "start": 801.6,
      "end": 802.54,
      "text": "이렇게 크쌤"
    },
    {
      "start": 802.54,
      "end": 803.52,
      "text": "들어오실 때마다"
    },
    {
      "start": 803.52,
      "end": 804.92,
      "text": "크쌤"
    },
    {
      "start": 804.92,
      "end": 805.5,
      "text": "안녕하세요"
    },
    {
      "start": 805.5,
      "end": 806.46,
      "text": "인사해 주시고"
    },
    {
      "start": 806.46,
      "end": 807.32,
      "text": "나가실 때마다"
    },
    {
      "start": 807.32,
      "end": 808.0,
      "text": "조크쌤"
    },
    {
      "start": 808.0,
      "end": 808.32,
      "text": "최고"
    },
    {
      "start": 808.32,
      "end": 809.82,
      "text": "아"
    },
    {
      "start": 809.82,
      "end": 810.38,
      "text": "이분이?"
    },
    {
      "start": 810.54,
      "end": 810.72,
      "text": "네."
    },
    {
      "start": 810.72,
      "end": 811.82,
      "text": "아니 이분뿐 아니라"
    },
    {
      "start": 811.82,
      "end": 812.6,
      "text": "많은 분들이"
    },
    {
      "start": 812.6,
      "end": 813.86,
      "text": "너무 감사해요."
    },
    {
      "start": 813.94,
      "end": 814.2,
      "text": "네."
    },
    {
      "start": 814.38,
      "end": 814.74,
      "text": "진짜"
    },
    {
      "start": 814.74,
      "end": 816.1,
      "text": "조크쌤의 매력"
    },
    {
      "start": 816.1,
      "end": 817.4,
      "text": "빠지셨죠."
    },
    {
      "start": 817.46,
      "end": 819.04,
      "text": "그러니까 빠져 빠져"
    },
    {
      "start": 819.04,
      "end": 819.6,
      "text": "그죠?"
    },
    {
      "start": 820.16,
      "end": 820.3,
      "text": "네."
    },
    {
      "start": 820.36,
      "end": 821.9,
      "text": "오늘 스크린 잉글리시는"
    },
    {
      "start": 821.9,
      "end": 822.84,
      "text": "여기까지고요."
    }
  ]
}